[{
        "name": "Brazier of Holy Fire",
        "class": "Melee",
        "range": "-",
        "rof": "-",
        "dmg": "1d10+5",
        "pen": 3,
        "type": "Energy",
        "clip": "-",
        "rld": "-",
        "special": "Flame, Unbalanced",
        "wt": 6,
        "rarity": "Very Rare",
        "training": "Flame",
        "description": "Any character who can draw line of sight to an ally wielding an active Brazier of Holy Fire gains a +10 bonus to his Willpower tests. Additionally, it can be used as a heavy lamer with a clip size of 1. Once ired, it loses the Flame quality in melee until it is reloaded, a process that takes roughly 20 minutes and involves several special hymns."
    },
    {
        "name": "Fire Gauntlets",
        "class": "Melee",
        "range": "-",
        "rof": "-",
        "dmg": "1d10",
        "pen": 2,
        "type": "Impact",
        "clip": "-",
        "rld": "-",
        "special": "Flame, Unbalanced",
        "wt": 1,
        "rarity": "Very Rare",
        "training": "Flame",
        "description": "As a Free Action, the user can ignite the gauntlets, granting a +20 bonus to Intimidate tests. They always come in pairs, and the reservoir lasts until the end of the encounter (or 2d10 minutes outside of structured time)."
    },
    {
        "name": "Axe of Retribution",
        "class": "Melee, Two-Handed",
        "range": "-",
        "rof": "-",
        "dmg": "2d10",
        "pen": 6,
        "type": "Rending",
        "clip": "-",
        "rld": "-",
        "special": "Felling (2), Sanctified",
        "wt": 8,
        "rarity": "Near Unique",
        "training": "Low-Tech"
    },
    {
        "name": "Flail of Chastisement",
        "class": "Melee",
        "range": "-",
        "rof": "-",
        "dmg": "1d10+3",
        "pen": 2,
        "type": "Rending",
        "clip": "-",
        "rld": "-",
        "special": "Crippling (2), Flexible, Primitive (8), Snare (0)",
        "wt": 3,
        "rarity": "Rare",
        "training": "Low-Tech",
        "description": "A target who escapes from this weapon’s Snare quality is no longer afected by its Crippling quality."
    },
    {
        "name": "Man-Catcher",
        "class": "Melee, Two-Handed",
        "range": 2,
        "rof": "-",
        "dmg": "1d10",
        "pen": 0,
        "type": "Impact",
        "clip": "-",
        "rld": "-",
        "special": "Snare (4), Unwieldy",
        "wt": 8,
        "rarity": "Scarce",
        "training": "Low-Tech",
        "description": "This is a two-handed weapon, and the user must spend a Half Action each round in order to maintain a hold of his victim. The Best craftsmanship version is itted with electrical wiring and gains the Shocking quality."
    },
    {
        "name": "Praesidium Protectiva",
        "class": "Melee",
        "range": "-",
        "rof": "-",
        "dmg": "1d10",
        "pen": 0,
        "type": "Impact",
        "clip": "-",
        "rld": "-",
        "special": "Defensive",
        "wt": 14,
        "rarity": "Very Rare",
        "training": "Low-Tech",
        "description": "The Praesidium Protectiva adds +4 AP to the body and the arm holding the device, and also acts as a force ield with a protection rating of 35. It is only available to Acolytes with the Adepta Sororitas background—those without it must provide a rationale to their GM when attempting to acquire this item."
    },
    {
        "name": "Power Stake",
        "class": "Melee",
        "range": "-",
        "rof": "-",
        "dmg": "1d10+7",
        "pen": 5,
        "type": "Energy",
        "clip": "-",
        "rld": "-",
        "special": "Power Field, Sanctified, Unbalanced",
        "wt": 1,
        "rarity": "Very Rare",
        "training": "Power",
        "description": "A power stake inlicts an additional 1d10 Energy damage for every point of psy rating the target possesses. Additionally, possessing a power stake grants a +10 bonus to all Interaction tests made with those aligned with the Ordo Hereticus."
    },
    {
        "name": "Electro-Flail",
        "class": "Melee",
        "range": "-",
        "rof": "-",
        "dmg": "1d10+2",
        "pen": 0,
        "type": "Rending",
        "clip": "-",
        "rld": "-",
        "special": "Flexible, Shocking",
        "wt": 4.5,
        "rarity": "Rare",
        "training": "Shock"
    }]